sampleOutput/verilog_code/dotprod.v
module dotprod (
	input	[31:0] n,
	output	[31:0] return_val,
	input	sys_clk,
	input	sys_rst_n
);
	
	reg [31:0] a_mem [0:255];
	reg [31:0] b_mem [0:255];
	reg [31:0] reg_i;
	reg [31:0] reg_cl;
	reg [31:0] reg_0;
	reg [31:0] reg_1;
	reg [31:0] reg_2;
	reg [3:0] cur_state;
	reg [3:0] last_state;
	reg branch_ready;
	reg [31:0] counter;
	reg [31:0] ret;
	
	parameter state_0 = 4'b1000;
	parameter state_start = 4'b0100;
	parameter state_calc = 4'b0010;
	parameter state_ret = 4'b0001;
	
	wire cond;
	
always @(posedge sys_clk or negedge sys_rst_n) begin
	if (!sys_rst_n) begin
		reg_0 <= 32'bx;
		reg_1 <= 32'bx;
		reg_2 <= 32'bx;
		reg_i <= 32'bx;
		reg_cl <= 32'bx;
		$readmemh("../../example/testbench/a.txt", a_mem);
		$readmemh("../../example/testbench/b.txt", b_mem);
		ret <= 32'bz;
		counter <= 32'b0;
		last_state <= state_0;
		cur_state <= state_0;
	end
	else begin
case (cur_state)
	state_0: begin
		case (counter)
			32'd0: begin
					reg_0 <= 0;
					branch_ready <= 1'b1;
			end
		endcase
	end
	state_start: begin
		case (counter)
			32'd0: begin
					if (last_state == state_0) reg_i <= 0;
					else if (last_state == state_calc) reg_i <= reg_2;
			end
			32'd1: begin
					if (last_state == state_0) reg_cl <= reg_0;
					else if (last_state == state_calc) reg_cl <= reg_1;
					reg_0 <= {31'b0, (reg_i >= n)};
			end
			32'd2: begin
					branch_ready <= 1'b1;
			end
		endcase
	end
	state_calc: begin
		case (counter)
			32'd0: begin
					reg_0 <= a_mem[reg_i];
					reg_2 <= reg_i + 1;
			end
			32'd1: begin
				
			end
			32'd2: begin
					reg_1 <= b_mem[reg_i];
			end
			32'd3: begin
				
			end
			32'd4: begin
					reg_0 <= reg_0 * reg_1;
			end
			32'd5: begin
				
			end
			32'd6: begin
				
			end
			32'd7: begin
				
			end
			32'd8: begin
				
			end
			32'd9: begin
					reg_1 <= reg_cl + reg_0;
					branch_ready <= 1'b1;
			end
		endcase
	end
	state_ret: begin
		case (counter)
			32'd0: begin
					ret <= reg_cl;
					branch_ready <= 1'b1;
			end
		endcase
	end
endcase
		if (cur_state == state_0 && branch_ready == 1'b1) begin
			last_state <= cur_state;
			cur_state <= state_start;
			branch_ready <= 1'b0;
			counter <= 32'b0;
		end
		else if (cur_state == state_start && branch_ready == 1'b1 && cond == 1'b1) begin
			last_state <= cur_state;
			cur_state <= state_ret;
			branch_ready <= 1'b0;
			counter <= 32'b0;
		end
		else if (cur_state == state_start && branch_ready == 1'b1 && cond == 1'b0) begin
			last_state <= cur_state;
			cur_state <= state_calc;
			branch_ready <= 1'b0;
			counter <= 32'b0;
		end
		else if (cur_state == state_calc && branch_ready == 1'b1) begin
			last_state <= cur_state;
			cur_state <= state_start;
			branch_ready <= 1'b0;
			counter <= 32'b0;
		end
		else begin
			counter <= counter + 1'b1;
		end
	end
end
	
assign return_val = ret;
assign cond = ((cur_state == state_start) & reg_0[0]);
	
endmodule

example/testbench/dotprod_tb.v
module dotprod_tb();
reg sys_clk;
reg sys_rst_n;
reg [31:0] n;
wire [31:0] return_val;

initial begin
    $dumpfile("dotprod_wave.vcd");
    $dumpvars(0, dotprod_tb);

    sys_clk <= 1'b0;
    sys_rst_n <= 1'b1;
    n <= 32'd10;
    #5 sys_rst_n <= 1'b0;
    #5 sys_rst_n <= 1'b1;
    #2000 $finish;
end

always #1 sys_clk <= ~sys_clk;

dotprod uut(.sys_clk(sys_clk), .sys_rst_n(sys_rst_n), .n(n), .return_val(return_val));
endmodule

sampleOutput/waveform/dotprod_wave.vcd
$date
	Wed Apr 23 16:43:28 2025
$end
$version
	Icarus Verilog
$end
$timescale
	1s
$end
$scope module dotprod_tb $end
$var wire 32 ! return_val [31:0] $end
$var reg 32 " n [31:0] $end
$var reg 1 # sys_clk $end
$var reg 1 $ sys_rst_n $end
$scope module uut $end
$var wire 1 % cond $end
$var wire 32 & n [31:0] $end
$var wire 32 ' return_val [31:0] $end
$var wire 1 # sys_clk $end
$var wire 1 $ sys_rst_n $end
$var parameter 4 ( state_0 $end
$var parameter 4 ) state_calc $end
$var parameter 4 * state_ret $end
$var parameter 4 + state_start $end
$var reg 1 , branch_ready $end
$var reg 32 - counter [31:0] $end
$var reg 4 . cur_state [3:0] $end
$var reg 4 / last_state [3:0] $end
$var reg 32 0 reg_0 [31:0] $end
$var reg 32 1 reg_1 [31:0] $end
$var reg 32 2 reg_2 [31:0] $end
$var reg 32 3 reg_cl [31:0] $end
$var reg 32 4 reg_i [31:0] $end
$var reg 32 5 ret [31:0] $end
$upscope $end
$upscope $end
$enddefinitions $end
$comment Show the parameter values. $end
$dumpall
b100 +
b1 *
b10 )
b1000 (
$end
#0
$dumpvars
bx 5
bx 4
bx 3
bx 2
bx 1
bx 0
bx /
bx .
bx -
x,
bx '
b1010 &
x%
1$
0#
b1010 "
bx !
$end
#1
1#
#2
0#
#3
1#
#4
0#
#5
0%
b1000 .
b1000 /
b0 -
bz !
bz '
bz 5
1#
0$
#6
0#
#7
1#
#8
0#
#9
1#
#10
0#
1$
#11
b1 -
1,
b0 0
1#
#12
0#
#13
b0 -
0,
b100 .
1#
#14
0#
#15
b1 -
b0 4
1#
#16
0#
#17
b10 -
b0 3
1#
#18
0#
#19
b11 -
1,
1#
#20
0#
#21
b0 -
0,
b10 .
b100 /
1#
#22
0#
#23
b1 -
b1 2
b1 0
1#
#24
0#
#25
b10 -
1#
#26
0#
#27
b11 -
b1 1
1#
#28
0#
#29
b100 -
1#
#30
0#
#31
b101 -
1#
#32
0#
#33
b110 -
1#
#34
0#
#35
b111 -
1#
#36
0#
#37
b1000 -
1#
#38
0#
#39
b1001 -
1#
#40
0#
#41
b1010 -
1,
1#
#42
0#
#43
1%
b0 -
0,
b100 .
b10 /
1#
#44
0#
#45
b1 -
b1 4
1#
#46
0#
#47
0%
b10 -
b0 0
b1 3
1#
#48
0#
#49
b11 -
1,
1#
#50
0#
#51
b0 -
0,
b10 .
b100 /
1#
#52
0#
#53
b1 -
b10 2
b10 0
1#
#54
0#
#55
b10 -
1#
#56
0#
#57
b11 -
1#
#58
0#
#59
b100 -
1#
#60
0#
#61
b101 -
1#
#62
0#
#63
b110 -
1#
#64
0#
#65
b111 -
1#
#66
0#
#67
b1000 -
1#
#68
0#
#69
b1001 -
1#
#70
0#
#71
b1010 -
1,
b11 1
1#
#72
0#
#73
b0 -
0,
b100 .
b10 /
1#
#74
0#
#75
b1 -
b10 4
1#
#76
0#
#77
b10 -
b0 0
b11 3
1#
#78
0#
#79
b11 -
1,
1#
#80
0#
#81
b0 -
0,
b10 .
b100 /
1#
#82
0#
#83
b1 -
b11 2
b11 0
1#
#84
0#
#85
b10 -
1#
#86
0#
#87
b11 -
b1 1
1#
#88
0#
#89
b100 -
1#
#90
0#
#91
b101 -
1#
#92
0#
#93
b110 -
1#
#94
0#
#95
b111 -
1#
#96
0#
#97
b1000 -
1#
#98
0#
#99
b1001 -
1#
#100
0#
#101
b1010 -
1,
b110 1
1#
#102
0#
#103
1%
b0 -
0,
b100 .
b10 /
1#
#104
0#
#105
b1 -
b11 4
1#
#106
0#
#107
0%
b10 -
b0 0
b110 3
1#
#108
0#
#109
b11 -
1,
1#
#110
0#
#111
b0 -
0,
b10 .
b100 /
1#
#112
0#
#113
b1 -
b100 2
b100 0
1#
#114
0#
#115
b10 -
1#
#116
0#
#117
b11 -
b1 1
1#
#118
0#
#119
b100 -
1#
#120
0#
#121
b101 -
1#
#122
0#
#123
b110 -
1#
#124
0#
#125
b111 -
1#
#126
0#
#127
b1000 -
1#
#128
0#
#129
b1001 -
1#
#130
0#
#131
b1010 -
1,
b1010 1
1#
#132
0#
#133
b0 -
0,
b100 .
b10 /
1#
#134
0#
#135
b1 -
b100 4
1#
#136
0#
#137
b10 -
b0 0
b1010 3
1#
#138
0#
#139
b11 -
1,
1#
#140
0#
#141
b0 -
0,
b10 .
b100 /
1#
#142
0#
#143
b1 -
b101 2
b101 0
1#
#144
0#
#145
b10 -
1#
#146
0#
#147
b11 -
b1 1
1#
#148
0#
#149
b100 -
1#
#150
0#
#151
b101 -
1#
#152
0#
#153
b110 -
1#
#154
0#
#155
b111 -
1#
#156
0#
#157
b1000 -
1#
#158
0#
#159
b1001 -
1#
#160
0#
#161
b1010 -
1,
b1111 1
1#
#162
0#
#163
1%
b0 -
0,
b100 .
b10 /
1#
#164
0#
#165
b1 -
b101 4
1#
#166
0#
#167
0%
b10 -
b0 0
b1111 3
1#
#168
0#
#169
b11 -
1,
1#
#170
0#
#171
b0 -
0,
b10 .
b100 /
1#
#172
0#
#173
b1 -
b110 2
b110 0
1#
#174
0#
#175
b10 -
1#
#176
0#
#177
b11 -
b1 1
1#
#178
0#
#179
b100 -
1#
#180
0#
#181
b101 -
1#
#182
0#
#183
b110 -
1#
#184
0#
#185
b111 -
1#
#186
0#
#187
b1000 -
1#
#188
0#
#189
b1001 -
1#
#190
0#
#191
b1010 -
1,
b10101 1
1#
#192
0#
#193
b0 -
0,
b100 .
b10 /
1#
#194
0#
#195
b1 -
b110 4
1#
#196
0#
#197
b10 -
b0 0
b10101 3
1#
#198
0#
#199
b11 -
1,
1#
#200
0#
#201
b0 -
0,
b10 .
b100 /
1#
#202
0#
#203
b1 -
b111 2
b111 0
1#
#204
0#
#205
b10 -
1#
#206
0#
#207
b11 -
b1 1
1#
#208
0#
#209
b100 -
1#
#210
0#
#211
b101 -
1#
#212
0#
#213
b110 -
1#
#214
0#
#215
b111 -
1#
#216
0#
#217
b1000 -
1#
#218
0#
#219
b1001 -
1#
#220
0#
#221
b1010 -
1,
b11100 1
1#
#222
0#
#223
1%
b0 -
0,
b100 .
b10 /
1#
#224
0#
#225
b1 -
b111 4
1#
#226
0#
#227
0%
b10 -
b0 0
b11100 3
1#
#228
0#
#229
b11 -
1,
1#
#230
0#
#231
b0 -
0,
b10 .
b100 /
1#
#232
0#
#233
b1 -
b1000 2
b1000 0
1#
#234
0#
#235
b10 -
1#
#236
0#
#237
b11 -
b1 1
1#
#238
0#
#239
b100 -
1#
#240
0#
#241
b101 -
1#
#242
0#
#243
b110 -
1#
#244
0#
#245
b111 -
1#
#246
0#
#247
b1000 -
1#
#248
0#
#249
b1001 -
1#
#250
0#
#251
b1010 -
1,
b100100 1
1#
#252
0#
#253
b0 -
0,
b100 .
b10 /
1#
#254
0#
#255
b1 -
b1000 4
1#
#256
0#
#257
b10 -
b0 0
b100100 3
1#
#258
0#
#259
b11 -
1,
1#
#260
0#
#261
b0 -
0,
b10 .
b100 /
1#
#262
0#
#263
b1 -
b1001 2
b1001 0
1#
#264
0#
#265
b10 -
1#
#266
0#
#267
b11 -
b1 1
1#
#268
0#
#269
b100 -
1#
#270
0#
#271
b101 -
1#
#272
0#
#273
b110 -
1#
#274
0#
#275
b111 -
1#
#276
0#
#277
b1000 -
1#
#278
0#
#279
b1001 -
1#
#280
0#
#281
b1010 -
1,
b101101 1
1#
#282
0#
#283
1%
b0 -
0,
b100 .
b10 /
1#
#284
0#
#285
b1 -
b1001 4
1#
#286
0#
#287
0%
b10 -
b0 0
b101101 3
1#
#288
0#
#289
b11 -
1,
1#
#290
0#
#291
b0 -
0,
b10 .
b100 /
1#
#292
0#
#293
b1 -
b1010 2
b1010 0
1#
#294
0#
#295
b10 -
1#
#296
0#
#297
b11 -
b1 1
1#
#298
0#
#299
b100 -
1#
#300
0#
#301
b101 -
1#
#302
0#
#303
b110 -
1#
#304
0#
#305
b111 -
1#
#306
0#
#307
b1000 -
1#
#308
0#
#309
b1001 -
1#
#310
0#
#311
b1010 -
1,
b110111 1
1#
#312
0#
#313
b0 -
0,
b100 .
b10 /
1#
#314
0#
#315
b1 -
b1010 4
1#
#316
0#
#317
1%
b10 -
b1 0
b110111 3
1#
#318
0#
#319
b11 -
1,
1#
#320
0#
#321
0%
b0 -
0,
b1 .
b100 /
1#
#322
0#
#323
b1 -
1,
b110111 !
b110111 '
b110111 5
1#
#324
0#
#325
b10 -
1#
#326
0#
#327
b11 -
1#
#328
0#
#329
b100 -
1#
#330
0#
#331
b101 -
1#
#332
0#
#333
b110 -
1#
#334
0#
#335
b111 -
1#
#336
0#
#337
b1000 -
1#
#338
0#
#339
b1001 -
1#
#340
0#
#341
b1010 -
1#
#342
0#
#343
b1011 -
1#
#344
0#
#345
b1100 -
1#
#346
0#
#347
b1101 -
1#
#348
0#
#349
b1110 -
1#
#350
0#
#351
b1111 -
1#
#352
0#
#353
b10000 -
1#
#354
0#
#355
b10001 -
1#
#356
0#
#357
b10010 -
1#
#358
0#
#359
b10011 -
1#
#360
0#
#361
b10100 -
1#
#362
0#
#363
b10101 -
1#
#364
0#
#365
b10110 -
1#
#366
0#
#367
b10111 -
1#
#368
0#
#369
b11000 -
1#
#370
0#
#371
b11001 -
1#
#372
0#
#373
b11010 -
1#
#374
0#
#375
b11011 -
1#
#376
0#
#377
b11100 -
1#
#378
0#
#379
b11101 -
1#
#380
0#
#381
b11110 -
1#
#382
0#
#383
b11111 -
1#
#384
0#
#385
b100000 -
1#
#386
0#
#387
b100001 -
1#
#388
0#
#389
b100010 -
1#
#390
0#
#391
b100011 -
1#
#392
0#
#393
b100100 -
1#
#394
0#
#395
b100101 -
1#
#396
0#
#397
b100110 -
1#
#398
0#
#399
b100111 -
1#
#400
0#
#401
b101000 -
1#
#402
0#
#403
b101001 -
1#
#404
0#
#405
b101010 -
1#
#406
0#
#407
b101011 -
1#
#408
0#
#409
b101100 -
1#
#410
0#
#411
b101101 -
1#
#412
0#
#413
b101110 -
1#
#414
0#
#415
b101111 -
1#
#416
0#
#417
b110000 -
1#
#418
0#
#419
b110001 -
1#
#420
0#
#421
b110010 -
1#
#422
0#
#423
b110011 -
1#
#424
0#
#425
b110100 -
1#
#426
0#
#427
b110101 -
1#
#428
0#
#429
b110110 -
1#
#430
0#
#431
b110111 -
1#
#432
0#
#433
b111000 -
1#
#434
0#
#435
b111001 -
1#
#436
0#
#437
b111010 -
1#
#438
0#
#439
b111011 -
1#
#440
0#
#441
b111100 -
1#
#442
0#
#443
b111101 -
1#
#444
0#
#445
b111110 -
1#
#446
0#
#447
b111111 -
1#
#448
0#
#449
b1000000 -
1#
#450
0#
#451
b1000001 -
1#
#452
0#
#453
b1000010 -
1#
#454
0#
#455
b1000011 -
1#
#456
0#
#457
b1000100 -
1#
#458
0#
#459
b1000101 -
1#
#460
0#
#461
b1000110 -
1#
#462
0#
#463
b1000111 -
1#
#464
0#
#465
b1001000 -
1#
#466
0#
#467
b1001001 -
1#
#468
0#
#469
b1001010 -
1#
#470
0#
#471
b1001011 -
1#
#472
0#
#473
b1001100 -
1#
#474
0#
#475
b1001101 -
1#
#476
0#
#477
b1001110 -
1#
#478
0#
#479
b1001111 -
1#
#480
0#
#481
b1010000 -
1#
#482
0#
#483
b1010001 -
1#
#484
0#
#485
b1010010 -
1#
#486
0#
#487
b1010011 -
1#
#488
0#
#489
b1010100 -
1#
#490
0#
#491
b1010101 -
1#
#492
0#
#493
b1010110 -
1#
#494
0#
#495
b1010111 -
1#
#496
0#
#497
b1011000 -
1#
#498
0#
#499
b1011001 -
1#
#500
0#
#501
b1011010 -
1#
#502
0#
#503
b1011011 -
1#
#504
0#
#505
b1011100 -
1#
#506
0#
#507
b1011101 -
1#
#508
0#
#509
b1011110 -
1#
#510
0#
#511
b1011111 -
1#
#512
0#
#513
b1100000 -
1#
#514
0#
#515
b1100001 -
1#
#516
0#
#517
b1100010 -
1#
#518
0#
#519
b1100011 -
1#
#520
0#
#521
b1100100 -
1#
#522
0#
#523
b1100101 -
1#
#524
0#
#525
b1100110 -
1#
#526
0#
#527
b1100111 -
1#
#528
0#
#529
b1101000 -
1#
#530
0#
#531
b1101001 -
1#
#532
0#
#533
b1101010 -
1#
#534
0#
#535
b1101011 -
1#
#536
0#
#537
b1101100 -
1#
#538
0#
#539
b1101101 -
1#
#540
0#
#541
b1101110 -
1#
#542
0#
#543
b1101111 -
1#
#544
0#
#545
b1110000 -
1#
#546
0#
#547
b1110001 -
1#
#548
0#
#549
b1110010 -
1#
#550
0#
#551
b1110011 -
1#
#552
0#
#553
b1110100 -
1#
#554
0#
#555
b1110101 -
1#
#556
0#
#557
b1110110 -
1#
#558
0#
#559
b1110111 -
1#
#560
0#
#561
b1111000 -
1#
#562
0#
#563
b1111001 -
1#
#564
0#
#565
b1111010 -
1#
#566
0#
#567
b1111011 -
1#
#568
0#
#569
b1111100 -
1#
#570
0#
#571
b1111101 -
1#
#572
0#
#573
b1111110 -
1#
#574
0#
#575
b1111111 -
1#
#576
0#
#577
b10000000 -
1#
#578
0#
#579
b10000001 -
1#
#580
0#
#581
b10000010 -
1#
#582
0#
#583
b10000011 -
1#
#584
0#
#585
b10000100 -
1#
#586
0#
#587
b10000101 -
1#
#588
0#
#589
b10000110 -
1#
#590
0#
#591
b10000111 -
1#
#592
0#
#593
b10001000 -
1#
#594
0#
#595
b10001001 -
1#
#596
0#
#597
b10001010 -
1#
#598
0#
#599
b10001011 -
1#
#600
0#
#601
b10001100 -
1#
#602
0#
#603
b10001101 -
1#
#604
0#
#605
b10001110 -
1#
#606
0#
#607
b10001111 -
1#
#608
0#
#609
b10010000 -
1#
#610
0#
#611
b10010001 -
1#
#612
0#
#613
b10010010 -
1#
#614
0#
#615
b10010011 -
1#
#616
0#
#617
b10010100 -
1#
#618
0#
#619
b10010101 -
1#
#620
0#
#621
b10010110 -
1#
#622
0#
#623
b10010111 -
1#
#624
0#
#625
b10011000 -
1#
#626
0#
#627
b10011001 -
1#
#628
0#
#629
b10011010 -
1#
#630
0#
#631
b10011011 -
1#
#632
0#
#633
b10011100 -
1#
#634
0#
#635
b10011101 -
1#
#636
0#
#637
b10011110 -
1#
#638
0#
#639
b10011111 -
1#
#640
0#
#641
b10100000 -
1#
#642
0#
#643
b10100001 -
1#
#644
0#
#645
b10100010 -
1#
#646
0#
#647
b10100011 -
1#
#648
0#
#649
b10100100 -
1#
#650
0#
#651
b10100101 -
1#
#652
0#
#653
b10100110 -
1#
#654
0#
#655
b10100111 -
1#
#656
0#
#657
b10101000 -
1#
#658
0#
#659
b10101001 -
1#
#660
0#
#661
b10101010 -
1#
#662
0#
#663
b10101011 -
1#
#664
0#
#665
b10101100 -
1#
#666
0#
#667
b10101101 -
1#
#668
0#
#669
b10101110 -
1#
#670
0#
#671
b10101111 -
1#
#672
0#
#673
b10110000 -
1#
#674
0#
#675
b10110001 -
1#
#676
0#
#677
b10110010 -
1#
#678
0#
#679
b10110011 -
1#
#680
0#
#681
b10110100 -
1#
#682
0#
#683
b10110101 -
1#
#684
0#
#685
b10110110 -
1#
#686
0#
#687
b10110111 -
1#
#688
0#
#689
b10111000 -
1#
#690
0#
#691
b10111001 -
1#
#692
0#
#693
b10111010 -
1#
#694
0#
#695
b10111011 -
1#
#696
0#
#697
b10111100 -
1#
#698
0#
#699
b10111101 -
1#
#700
0#
#701
b10111110 -
1#
#702
0#
#703
b10111111 -
1#
#704
0#
#705
b11000000 -
1#
#706
0#
#707
b11000001 -
1#
#708
0#
#709
b11000010 -
1#
#710
0#
#711
b11000011 -
1#
#712
0#
#713
b11000100 -
1#
#714
0#
#715
b11000101 -
1#
#716
0#
#717
b11000110 -
1#
#718
0#
#719
b11000111 -
1#
#720
0#
#721
b11001000 -
1#
#722
0#
#723
b11001001 -
1#
#724
0#
#725
b11001010 -
1#
#726
0#
#727
b11001011 -
1#
#728
0#
#729
b11001100 -
1#
#730
0#
#731
b11001101 -
1#
#732
0#
#733
b11001110 -
1#
#734
0#
#735
b11001111 -
1#
#736
0#
#737
b11010000 -
1#
#738
0#
#739
b11010001 -
1#
#740
0#
#741
b11010010 -
1#
#742
0#
#743
b11010011 -
1#
#744
0#
#745
b11010100 -
1#
#746
0#
#747
b11010101 -
1#
#748
0#
#749
b11010110 -
1#
#750
0#
#751
b11010111 -
1#
#752
0#
#753
b11011000 -
1#
#754
0#
#755
b11011001 -
1#
#756
0#
#757
b11011010 -
1#
#758
0#
#759
b11011011 -
1#
#760
0#
#761
b11011100 -
1#
#762
0#
#763
b11011101 -
1#
#764
0#
#765
b11011110 -
1#
#766
0#
#767
b11011111 -
1#
#768
0#
#769
b11100000 -
1#
#770
0#
#771
b11100001 -
1#
#772
0#
#773
b11100010 -
1#
#774
0#
#775
b11100011 -
1#
#776
0#
#777
b11100100 -
1#
#778
0#
#779
b11100101 -
1#
#780
0#
#781
b11100110 -
1#
#782
0#
#783
b11100111 -
1#
#784
0#
#785
b11101000 -
1#
#786
0#
#787
b11101001 -
1#
#788
0#
#789
b11101010 -
1#
#790
0#
#791
b11101011 -
1#
#792
0#
#793
b11101100 -
1#
#794
0#
#795
b11101101 -
1#
#796
0#
#797
b11101110 -
1#
#798
0#
#799
b11101111 -
1#
#800
0#
#801
b11110000 -
1#
#802
0#
#803
b11110001 -
1#
#804
0#
#805
b11110010 -
1#
#806
0#
#807
b11110011 -
1#
#808
0#
#809
b11110100 -
1#
#810
0#
#811
b11110101 -
1#
#812
0#
#813
b11110110 -
1#
#814
0#
#815
b11110111 -
1#
#816
0#
#817
b11111000 -
1#
#818
0#
#819
b11111001 -
1#
#820
0#
#821
b11111010 -
1#
#822
0#
#823
b11111011 -
1#
#824
0#
#825
b11111100 -
1#
#826
0#
#827
b11111101 -
1#
#828
0#
#829
b11111110 -
1#
#830
0#
#831
b11111111 -
1#
#832
0#
#833
b100000000 -
1#
#834
0#
#835
b100000001 -
1#
#836
0#
#837
b100000010 -
1#
#838
0#
#839
b100000011 -
1#
#840
0#
#841
b100000100 -
1#
#842
0#
#843
b100000101 -
1#
#844
0#
#845
b100000110 -
1#
#846
0#
#847
b100000111 -
1#
#848
0#
#849
b100001000 -
1#
#850
0#
#851
b100001001 -
1#
#852
0#
#853
b100001010 -
1#
#854
0#
#855
b100001011 -
1#
#856
0#
#857
b100001100 -
1#
#858
0#
#859
b100001101 -
1#
#860
0#
#861
b100001110 -
1#
#862
0#
#863
b100001111 -
1#
#864
0#
#865
b100010000 -
1#
#866
0#
#867
b100010001 -
1#
#868
0#
#869
b100010010 -
1#
#870
0#
#871
b100010011 -
1#
#872
0#
#873
b100010100 -
1#
#874
0#
#875
b100010101 -
1#
#876
0#
#877
b100010110 -
1#
#878
0#
#879
b100010111 -
1#
#880
0#
#881
b100011000 -
1#
#882
0#
#883
b100011001 -
1#
#884
0#
#885
b100011010 -
1#
#886
0#
#887
b100011011 -
1#
#888
0#
#889
b100011100 -
1#
#890
0#
#891
b100011101 -
1#
#892
0#
#893
b100011110 -
1#
#894
0#
#895
b100011111 -
1#
#896
0#
#897
b100100000 -
1#
#898
0#
#899
b100100001 -
1#
#900
0#
#901
b100100010 -
1#
#902
0#
#903
b100100011 -
1#
#904
0#
#905
b100100100 -
1#
#906
0#
#907
b100100101 -
1#
#908
0#
#909
b100100110 -
1#
#910
0#
#911
b100100111 -
1#
#912
0#
#913
b100101000 -
1#
#914
0#
#915
b100101001 -
1#
#916
0#
#917
b100101010 -
1#
#918
0#
#919
b100101011 -
1#
#920
0#
#921
b100101100 -
1#
#922
0#
#923
b100101101 -
1#
#924
0#
#925
b100101110 -
1#
#926
0#
#927
b100101111 -
1#
#928
0#
#929
b100110000 -
1#
#930
0#
#931
b100110001 -
1#
#932
0#
#933
b100110010 -
1#
#934
0#
#935
b100110011 -
1#
#936
0#
#937
b100110100 -
1#
#938
0#
#939
b100110101 -
1#
#940
0#
#941
b100110110 -
1#
#942
0#
#943
b100110111 -
1#
#944
0#
#945
b100111000 -
1#
#946
0#
#947
b100111001 -
1#
#948
0#
#949
b100111010 -
1#
#950
0#
#951
b100111011 -
1#
#952
0#
#953
b100111100 -
1#
#954
0#
#955
b100111101 -
1#
#956
0#
#957
b100111110 -
1#
#958
0#
#959
b100111111 -
1#
#960
0#
#961
b101000000 -
1#
#962
0#
#963
b101000001 -
1#
#964
0#
#965
b101000010 -
1#
#966
0#
#967
b101000011 -
1#
#968
0#
#969
b101000100 -
1#
#970
0#
#971
b101000101 -
1#
#972
0#
#973
b101000110 -
1#
#974
0#
#975
b101000111 -
1#
#976
0#
#977
b101001000 -
1#
#978
0#
#979
b101001001 -
1#
#980
0#
#981
b101001010 -
1#
#982
0#
#983
b101001011 -
1#
#984
0#
#985
b101001100 -
1#
#986
0#
#987
b101001101 -
1#
#988
0#
#989
b101001110 -
1#
#990
0#
#991
b101001111 -
1#
#992
0#
#993
b101010000 -
1#
#994
0#
#995
b101010001 -
1#
#996
0#
#997
b101010010 -
1#
#998
0#
#999
b101010011 -
1#
#1000
0#
#1001
b101010100 -
1#
#1002
0#
#1003
b101010101 -
1#
#1004
0#
#1005
b101010110 -
1#
#1006
0#
#1007
b101010111 -
1#
#1008
0#
#1009
b101011000 -
1#
#1010
0#
#1011
b101011001 -
1#
#1012
0#
#1013
b101011010 -
1#
#1014
0#
#1015
b101011011 -
1#
#1016
0#
#1017
b101011100 -
1#
#1018
0#
#1019
b101011101 -
1#
#1020
0#
#1021
b101011110 -
1#
#1022
0#
#1023
b101011111 -
1#
#1024
0#
#1025
b101100000 -
1#
#1026
0#
#1027
b101100001 -
1#
#1028
0#
#1029
b101100010 -
1#
#1030
0#
#1031
b101100011 -
1#
#1032
0#
#1033
b101100100 -
1#
#1034
0#
#1035
b101100101 -
1#
#1036
0#
#1037
b101100110 -
1#
#1038
0#
#1039
b101100111 -
1#
#1040
0#
#1041
b101101000 -
1#
#1042
0#
#1043
b101101001 -
1#
#1044
0#
#1045
b101101010 -
1#
#1046
0#
#1047
b101101011 -
1#
#1048
0#
#1049
b101101100 -
1#
#1050
0#
#1051
b101101101 -
1#
#1052
0#
#1053
b101101110 -
1#
#1054
0#
#1055
b101101111 -
1#
#1056
0#
#1057
b101110000 -
1#
#1058
0#
#1059
b101110001 -
1#
#1060
0#
#1061
b101110010 -
1#
#1062
0#
#1063
b101110011 -
1#
#1064
0#
#1065
b101110100 -
1#
#1066
0#
#1067
b101110101 -
1#
#1068
0#
#1069
b101110110 -
1#
#1070
0#
#1071
b101110111 -
1#
#1072
0#
#1073
b101111000 -
1#
#1074
0#
#1075
b101111001 -
1#
#1076
0#
#1077
b101111010 -
1#
#1078
0#
#1079
b101111011 -
1#
#1080
0#
#1081
b101111100 -
1#
#1082
0#
#1083
b101111101 -
1#
#1084
0#
#1085
b101111110 -
1#
#1086
0#
#1087
b101111111 -
1#
#1088
0#
#1089
b110000000 -
1#
#1090
0#
#1091
b110000001 -
1#
#1092
0#
#1093
b110000010 -
1#
#1094
0#
#1095
b110000011 -
1#
#1096
0#
#1097
b110000100 -
1#
#1098
0#
#1099
b110000101 -
1#
#1100
0#
#1101
b110000110 -
1#
#1102
0#
#1103
b110000111 -
1#
#1104
0#
#1105
b110001000 -
1#
#1106
0#
#1107
b110001001 -
1#
#1108
0#
#1109
b110001010 -
1#
#1110
0#
#1111
b110001011 -
1#
#1112
0#
#1113
b110001100 -
1#
#1114
0#
#1115
b110001101 -
1#
#1116
0#
#1117
b110001110 -
1#
#1118
0#
#1119
b110001111 -
1#
#1120
0#
#1121
b110010000 -
1#
#1122
0#
#1123
b110010001 -
1#
#1124
0#
#1125
b110010010 -
1#
#1126
0#
#1127
b110010011 -
1#
#1128
0#
#1129
b110010100 -
1#
#1130
0#
#1131
b110010101 -
1#
#1132
0#
#1133
b110010110 -
1#
#1134
0#
#1135
b110010111 -
1#
#1136
0#
#1137
b110011000 -
1#
#1138
0#
#1139
b110011001 -
1#
#1140
0#
#1141
b110011010 -
1#
#1142
0#
#1143
b110011011 -
1#
#1144
0#
#1145
b110011100 -
1#
#1146
0#
#1147
b110011101 -
1#
#1148
0#
#1149
b110011110 -
1#
#1150
0#
#1151
b110011111 -
1#
#1152
0#
#1153
b110100000 -
1#
#1154
0#
#1155
b110100001 -
1#
#1156
0#
#1157
b110100010 -
1#
#1158
0#
#1159
b110100011 -
1#
#1160
0#
#1161
b110100100 -
1#
#1162
0#
#1163
b110100101 -
1#
#1164
0#
#1165
b110100110 -
1#
#1166
0#
#1167
b110100111 -
1#
#1168
0#
#1169
b110101000 -
1#
#1170
0#
#1171
b110101001 -
1#
#1172
0#
#1173
b110101010 -
1#
#1174
0#
#1175
b110101011 -
1#
#1176
0#
#1177
b110101100 -
1#
#1178
0#
#1179
b110101101 -
1#
#1180
0#
#1181
b110101110 -
1#
#1182
0#
#1183
b110101111 -
1#
#1184
0#
#1185
b110110000 -
1#
#1186
0#
#1187
b110110001 -
1#
#1188
0#
#1189
b110110010 -
1#
#1190
0#
#1191
b110110011 -
1#
#1192
0#
#1193
b110110100 -
1#
#1194
0#
#1195
b110110101 -
1#
#1196
0#
#1197
b110110110 -
1#
#1198
0#
#1199
b110110111 -
1#
#1200
0#
#1201
b110111000 -
1#
#1202
0#
#1203
b110111001 -
1#
#1204
0#
#1205
b110111010 -
1#
#1206
0#
#1207
b110111011 -
1#
#1208
0#
#1209
b110111100 -
1#
#1210
0#
#1211
b110111101 -
1#
#1212
0#
#1213
b110111110 -
1#
#1214
0#
#1215
b110111111 -
1#
#1216
0#
#1217
b111000000 -
1#
#1218
0#
#1219
b111000001 -
1#
#1220
0#
#1221
b111000010 -
1#
#1222
0#
#1223
b111000011 -
1#
#1224
0#
#1225
b111000100 -
1#
#1226
0#
#1227
b111000101 -
1#
#1228
0#
#1229
b111000110 -
1#
#1230
0#
#1231
b111000111 -
1#
#1232
0#
#1233
b111001000 -
1#
#1234
0#
#1235
b111001001 -
1#
#1236
0#
#1237
b111001010 -
1#
#1238
0#
#1239
b111001011 -
1#
#1240
0#
#1241
b111001100 -
1#
