sampleOutput/verilog_code/gcd.v
module gcd (
	input	[31:0] b,
	input	[31:0] a,
	output	[31:0] return_val,
	input	sys_clk,
	input	sys_rst_n
);
	
	reg [31:0] reg_a1;
	reg [31:0] reg_b1;
	reg [31:0] reg_divisor;
	reg [31:0] reg_remainder;
	reg [31:0] reg_0;
	reg [31:0] reg_1;
	reg [4:0] cur_state;
	reg [4:0] last_state;
	reg branch_ready;
	reg [31:0] counter;
	reg [31:0] ret;
	
	parameter state_0 = 5'b10000;
	parameter state_start = 5'b01000;
	parameter state_cal = 5'b00100;
	parameter state_exchange = 5'b00010;
	parameter state_ret = 5'b00001;
	
	wire a_LE_b;
	wire cond;
	
always @(posedge sys_clk or negedge sys_rst_n) begin
	if (!sys_rst_n) begin
		reg_0 <= 32'bx;
		reg_1 <= 32'bx;
		reg_a1 <= 32'bx;
		reg_b1 <= 32'bx;
		reg_divisor <= 32'bx;
		reg_remainder <= 32'bx;
		ret <= 32'bz;
		counter <= 32'b0;
		last_state <= state_0;
		cur_state <= state_0;
	end
	else begin
case (cur_state)
	state_0: begin
		case (counter)
			32'd0: begin
					reg_0 <= a;
			end
			32'd1: begin
					reg_1 <= b;
					branch_ready <= 1'b1;
			end
		endcase
	end
	state_start: begin
		case (counter)
			32'd0: begin
					if (last_state == state_0) reg_a1 <= reg_0;
					else if (last_state == state_cal) reg_a1 <= reg_divisor;
			end
			32'd1: begin
					if (last_state == state_0) reg_b1 <= reg_1;
					else if (last_state == state_cal) reg_b1 <= reg_remainder;
			end
			32'd2: begin
					reg_0 <= {31'b0, (reg_a1 >= reg_b1)};
			end
			32'd3: begin
					branch_ready <= 1'b1;
			end
		endcase
	end
	state_cal: begin
		case (counter)
			32'd0: begin
					if (last_state == state_start) reg_divisor <= reg_b1;
					else if (last_state == state_exchange) reg_divisor <= reg_a1;
			end
			32'd1: begin
					if (last_state == state_start) reg_0 <= reg_a1;
					else if (last_state == state_exchange) reg_0 <= reg_b1;
			end
			32'd2: begin
					reg_remainder <= reg_0 - reg_divisor;
			end
			32'd3: begin
					reg_0 <= {31'b0, (reg_remainder == 0)};
			end
			32'd4: begin
					branch_ready <= 1'b1;
			end
		endcase
	end
	state_exchange: begin
		case (counter)
			32'd0: begin
					branch_ready <= 1'b1;
			end
		endcase
	end
	state_ret: begin
		case (counter)
			32'd0: begin
					ret <= reg_divisor;
					branch_ready <= 1'b1;
			end
		endcase
	end
endcase
		if (cur_state == state_0 && branch_ready == 1'b1) begin
			last_state <= cur_state;
			cur_state <= state_start;
			branch_ready <= 1'b0;
			counter <= 32'b0;
		end
		else if (cur_state == state_start && branch_ready == 1'b1 && a_LE_b == 1'b1) begin
			last_state <= cur_state;
			cur_state <= state_cal;
			branch_ready <= 1'b0;
			counter <= 32'b0;
		end
		else if (cur_state == state_start && branch_ready == 1'b1 && a_LE_b == 1'b0) begin
			last_state <= cur_state;
			cur_state <= state_exchange;
			branch_ready <= 1'b0;
			counter <= 32'b0;
		end
		else if (cur_state == state_cal && branch_ready == 1'b1 && cond == 1'b1) begin
			last_state <= cur_state;
			cur_state <= state_ret;
			branch_ready <= 1'b0;
			counter <= 32'b0;
		end
		else if (cur_state == state_cal && branch_ready == 1'b1 && cond == 1'b0) begin
			last_state <= cur_state;
			cur_state <= state_start;
			branch_ready <= 1'b0;
			counter <= 32'b0;
		end
		else if (cur_state == state_exchange && branch_ready == 1'b1) begin
			last_state <= cur_state;
			cur_state <= state_cal;
			branch_ready <= 1'b0;
			counter <= 32'b0;
		end
		else begin
			counter <= counter + 1'b1;
		end
	end
end
	
assign return_val = ret;
assign a_LE_b = ((cur_state == state_start) & reg_0[0]);
assign cond = ((cur_state == state_cal) & reg_0[0]);
	
endmodule

example/testbench/gcd_tb.v
module gcd_tb;
	reg sys_clk;
	reg sys_rst_n;
	reg [31:0] a;
	reg [31:0] b;
	wire [31:0] return_val;

	initial begin
		$dumpfile("gcd_wave.vcd");
		$dumpvars(0, gcd_tb);

		sys_clk <= 1'b0;
		sys_rst_n <= 1'b1;
		#10 begin
			a <= 32'd28;
			b <= 32'd42;
		end
		#5 sys_rst_n <= 1'b0;
		#5 sys_rst_n <= 1'b1;
		#2000 $finish;
	end

	always #1 sys_clk = ~sys_clk;

	gcd uut (.sys_clk(sys_clk), .sys_rst_n(sys_rst_n), .return_val(return_val), .a(a), .b(b));

endmodule

sampleOutput/waveform/gcd_wave.vcd
$date
	Sat Apr 26 20:29:42 2025
$end
$version
	Icarus Verilog
$end
$timescale
	1s
$end
$scope module gcd_tb $end
$var wire 32 ! return_val [31:0] $end
$var reg 32 " a [31:0] $end
$var reg 32 # b [31:0] $end
$var reg 1 $ sys_clk $end
$var reg 1 % sys_rst_n $end
$scope module uut $end
$var wire 32 & a [31:0] $end
$var wire 1 ' a_LE_b $end
$var wire 32 ( b [31:0] $end
$var wire 1 ) cond $end
$var wire 32 * return_val [31:0] $end
$var wire 1 $ sys_clk $end
$var wire 1 % sys_rst_n $end
$var parameter 5 + state_0 $end
$var parameter 5 , state_cal $end
$var parameter 5 - state_exchange $end
$var parameter 5 . state_ret $end
$var parameter 5 / state_start $end
$var reg 1 0 branch_ready $end
$var reg 32 1 counter [31:0] $end
$var reg 5 2 cur_state [4:0] $end
$var reg 5 3 last_state [4:0] $end
$var reg 32 4 reg_0 [31:0] $end
$var reg 32 5 reg_1 [31:0] $end
$var reg 32 6 reg_a1 [31:0] $end
$var reg 32 7 reg_b1 [31:0] $end
$var reg 32 8 reg_divisor [31:0] $end
$var reg 32 9 reg_remainder [31:0] $end
$var reg 32 : ret [31:0] $end
$upscope $end
$upscope $end
$enddefinitions $end
$comment Show the parameter values. $end
$dumpall
b1000 /
b1 .
b10 -
b100 ,
b10000 +
$end
#0
$dumpvars
bx :
bx 9
bx 8
bx 7
bx 6
bx 5
bx 4
bx 3
bx 2
bx 1
x0
bx *
x)
bx (
x'
bx &
1%
0$
bx #
bx "
bx !
$end
#1
1$
#2
0$
#3
1$
#4
0$
#5
1$
#6
0$
#7
1$
#8
0$
#9
1$
#10
b101010 #
b101010 (
b11100 "
b11100 &
0$
#11
1$
#12
0$
#13
1$
#14
0$
#15
0'
0)
b10000 2
b10000 3
b0 1
bz !
bz *
bz :
0%
1$
#16
0$
#17
1$
#18
0$
#19
1$
#20
1%
0$
#21
b1 1
b11100 4
1$
#22
0$
#23
b10 1
10
b101010 5
1$
#24
0$
#25
b0 1
00
b1000 2
1$
#26
0$
#27
b1 1
b11100 6
1$
#28
0$
#29
b10 1
b101010 7
1$
#30
0$
#31
b11 1
b0 4
1$
#32
0$
#33
b100 1
10
1$
#34
0$
#35
b0 1
00
b10 2
b1000 3
1$
#36
0$
#37
b1 1
10
1$
#38
0$
#39
b0 1
00
b100 2
b10 3
1$
#40
0$
#41
b1 1
b11100 8
1$
#42
0$
#43
b10 1
b101010 4
1$
#44
0$
#45
b11 1
b1110 9
1$
#46
0$
#47
b100 1
b0 4
1$
#48
0$
#49
b101 1
10
1$
#50
0$
#51
b0 1
00
b1000 2
b100 3
1$
#52
0$
#53
b1 1
1$
#54
0$
#55
b10 1
b1110 7
1$
#56
0$
#57
1'
b11 1
b1 4
1$
#58
0$
#59
b100 1
10
1$
#60
0$
#61
0'
1)
b0 1
00
b100 2
b1000 3
1$
#62
0$
#63
b1 1
b1110 8
1$
#64
0$
#65
0)
b10 1
b11100 4
1$
#66
0$
#67
b11 1
1$
#68
0$
#69
b100 1
b0 4
1$
#70
0$
#71
b101 1
10
1$
#72
0$
#73
b0 1
00
b1000 2
b100 3
1$
#74
0$
#75
b1 1
b1110 6
1$
#76
0$
#77
b10 1
1$
#78
0$
#79
1'
b11 1
b1 4
1$
#80
0$
#81
b100 1
10
1$
#82
0$
#83
0'
1)
b0 1
00
b100 2
b1000 3
1$
#84
0$
#85
b1 1
1$
#86
0$
#87
0)
b10 1
b1110 4
1$
#88
0$
#89
b11 1
b0 9
1$
#90
0$
#91
1)
b100 1
b1 4
1$
#92
0$
#93
b101 1
10
1$
#94
0$
#95
0)
b0 1
00
b1 2
b100 3
1$
#96
0$
#97
b1 1
10
b1110 !
b1110 *
b1110 :
1$
#98
0$
#99
b10 1
1$
#100
0$
#101
b11 1
1$
#102
0$
#103
b100 1
1$
#104
0$
#105
b101 1
1$
#106
0$
#107
b110 1
1$
#108
0$
#109
b111 1
1$
#110
0$
#111
b1000 1
1$
#112
0$
#113
b1001 1
1$
#114
0$
#115
b1010 1
1$
#116
0$
#117
b1011 1
1$
#118
0$
#119
b1100 1
1$
#120
0$
#121
b1101 1
1$
#122
0$
#123
b1110 1
1$
#124
0$
#125
b1111 1
1$
#126
0$
#127
b10000 1
1$
#128
0$
#129
b10001 1
1$
#130
0$
#131
b10010 1
1$
#132
0$
#133
b10011 1
1$
#134
0$
#135
b10100 1
1$
#136
0$
#137
b10101 1
1$
#138
0$
#139
b10110 1
1$
#140
0$
#141
b10111 1
1$
#142
0$
#143
b11000 1
1$
#144
0$
#145
b11001 1
1$
#146
0$
#147
b11010 1
1$
#148
0$
#149
b11011 1
1$
#150
0$
#151
b11100 1
1$
#152
0$
#153
b11101 1
1$
#154
0$
#155
b11110 1
1$
#156
0$
#157
b11111 1
1$
#158
0$
#159
b100000 1
1$
#160
0$
#161
b100001 1
1$
#162
0$
#163
b100010 1
1$
#164
0$
#165
b100011 1
1$
#166
0$
#167
b100100 1
1$
#168
0$
#169
b100101 1
1$
#170
0$
#171
b100110 1
1$
#172
0$
#173
b100111 1
1$
#174
0$
#175
b101000 1
1$
#176
0$
#177
b101001 1
1$
#178
0$
#179
b101010 1
1$
#180
0$
#181
b101011 1
1$
#182
0$
#183
b101100 1
1$
#184
0$
#185
b101101 1
1$
#186
0$
#187
b101110 1
1$
#188
0$
#189
b101111 1
1$
#190
0$
#191
b110000 1
1$
#192
0$
#193
b110001 1
1$
#194
0$
#195
b110010 1
1$
#196
0$
#197
b110011 1
1$
#198
0$
#199
b110100 1
1$
#200
0$
#201
b110101 1
1$
#202
0$
#203
b110110 1
1$
#204
0$
#205
b110111 1
1$
#206
0$
#207
b111000 1
1$
#208
0$
#209
b111001 1
1$
#210
0$
#211
b111010 1
1$
#212
0$
#213
b111011 1
1$
#214
0$
#215
b111100 1
1$
#216
0$
#217
b111101 1
1$
#218
0$
#219
b111110 1
1$
#220
0$
#221
b111111 1
1$
#222
0$
#223
b1000000 1
1$
#224
0$
#225
b1000001 1
1$
#226
0$
#227
b1000010 1
1$
#228
0$
#229
b1000011 1
1$
#230
0$
#231
b1000100 1
1$
#232
0$
#233
b1000101 1
1$
#234
0$
#235
b1000110 1
1$
#236
0$
#237
b1000111 1
1$
#238
0$
#239
b1001000 1
1$
#240
0$
#241
b1001001 1
1$
#242
0$
#243
b1001010 1
1$
#244
0$
#245
b1001011 1
1$
#246
0$
#247
b1001100 1
1$
#248
0$
#249
b1001101 1
1$
#250
0$
#251
b1001110 1
1$
#252
0$
#253
b1001111 1
1$
#254
0$
#255
b1010000 1
1$
#256
0$
#257
b1010001 1
1$
#258
0$
#259
b1010010 1
1$
#260
0$
#261
b1010011 1
1$
#262
0$
#263
b1010100 1
1$
#264
0$
#265
b1010101 1
1$
#266
0$
#267
b1010110 1
1$
#268
0$
#269
b1010111 1
1$
#270
0$
#271
b1011000 1
1$
#272
0$
#273
b1011001 1
1$
#274
0$
#275
b1011010 1
1$
#276
0$
#277
b1011011 1
1$
#278
0$
#279
b1011100 1
1$
#280
0$
#281
b1011101 1
1$
#282
0$
#283
b1011110 1
1$
#284
0$
#285
b1011111 1
1$
#286
0$
#287
b1100000 1
1$
#288
0$
#289
b1100001 1
1$
#290
0$
#291
b1100010 1
1$
#292
0$
#293
b1100011 1
1$
#294
0$
#295
b1100100 1
1$
#296
0$
#297
b1100101 1
1$
#298
0$
#299
b1100110 1
1$
#300
0$
#301
b1100111 1
1$
#302
0$
#303
b1101000 1
1$
#304
0$
#305
b1101001 1
1$
#306
0$
#307
b1101010 1
1$
#308
0$
#309
b1101011 1
1$
#310
0$
#311
b1101100 1
1$
#312
0$
#313
b1101101 1
1$
#314
0$
#315
b1101110 1
1$
#316
0$
#317
b1101111 1
1$
#318
0$
#319
b1110000 1
1$
#320
0$
#321
b1110001 1
1$
#322
0$
#323
b1110010 1
1$
#324
0$
#325
b1110011 1
1$
#326
0$
#327
b1110100 1
1$
#328
0$
#329
b1110101 1
1$
#330
0$
#331
b1110110 1
1$
#332
0$
#333
b1110111 1
1$
#334
0$
#335
b1111000 1
1$
#336
0$
#337
b1111001 1
1$
#338
0$
#339
b1111010 1
1$
#340
0$
#341
b1111011 1
1$
#342
0$
#343
b1111100 1
1$
#344
0$
#345
b1111101 1
1$
#346
0$
#347
b1111110 1
1$
#348
0$
#349
b1111111 1
1$
#350
0$
#351
b10000000 1
1$
#352
0$
#353
b10000001 1
1$
#354
0$
#355
b10000010 1
1$
#356
0$
#357
b10000011 1
1$
#358
0$
#359
b10000100 1
1$
#360
0$
#361
b10000101 1
1$
#362
0$
#363
b10000110 1
1$
#364
0$
#365
b10000111 1
1$
#366
0$
#367
b10001000 1
1$
#368
0$
#369
b10001001 1
1$
#370
0$
#371
b10001010 1
1$
#372
0$
#373
b10001011 1
1$
#374
0$
#375
b10001100 1
1$
#376
0$
#377
b10001101 1
1$
#378
0$
#379
b10001110 1
1$
#380
0$
#381
b10001111 1
1$
#382
0$
#383
b10010000 1
1$
#384
0$
#385
b10010001 1
1$
#386
0$
#387
b10010010 1
1$
#388
0$
#389
b10010011 1
1$
#390
0$
#391
b10010100 1
1$
#392
0$
#393
b10010101 1
1$
#394
0$
#395
b10010110 1
1$
#396
0$
#397
b10010111 1
1$
#398
0$
#399
b10011000 1
1$
#400
0$
#401
b10011001 1
1$
#402
0$
#403
b10011010 1
1$
#404
0$
#405
b10011011 1
1$
#406
0$
#407
b10011100 1
1$
#408
0$
#409
b10011101 1
1$
#410
0$
#411
b10011110 1
1$
#412
0$
#413
b10011111 1
1$
#414
0$
#415
b10100000 1
1$
#416
0$
#417
b10100001 1
1$
#418
0$
#419
b10100010 1
1$
#420
0$
#421
b10100011 1
1$
#422
0$
#423
b10100100 1
1$
#424
0$
#425
b10100101 1
1$
#426
0$
#427
b10100110 1
1$
#428
0$
#429
b10100111 1
1$
#430
0$
#431
b10101000 1
1$
#432
0$
#433
b10101001 1
1$
#434
0$
#435
b10101010 1
1$
#436
0$
#437
b10101011 1
1$
#438
0$
#439
b10101100 1
1$
#440
0$
#441
b10101101 1
1$
#442
0$
#443
b10101110 1
1$
#444
0$
#445
b10101111 1
1$
#446
0$
#447
b10110000 1
1$
#448
0$
#449
b10110001 1
1$
#450
0$
#451
b10110010 1
1$
#452
0$
#453
b10110011 1
1$
#454
0$
#455
b10110100 1
1$
#456
0$
#457
b10110101 1
1$
#458
0$
#459
b10110110 1
1$
#460
0$
#461
b10110111 1
1$
#462
0$
#463
b10111000 1
1$
#464
0$
#465
b10111001 1
1$
#466
0$
#467
b10111010 1
1$
#468
0$
#469
b10111011 1
1$
#470
0$
#471
b10111100 1
1$
#472
0$
#473
b10111101 1
1$
#474
0$
#475
b10111110 1
1$
#476
0$
#477
b10111111 1
1$
#478
0$
#479
b11000000 1
1$
#480
0$
#481
b11000001 1
1$
#482
0$
#483
b11000010 1
1$
#484
0$
#485
b11000011 1
1$
#486
0$
#487
b11000100 1
1$
#488
0$
#489
b11000101 1
1$
#490
0$
#491
b11000110 1
1$
#492
0$
#493
b11000111 1
1$
#494
0$
#495
b11001000 1
1$
#496
0$
#497
b11001001 1
1$
#498
0$
#499
b11001010 1
1$
#500
0$
#501
b11001011 1
1$
#502
0$
#503
b11001100 1
1$
#504
0$
#505
b11001101 1
1$
#506
0$
#507
b11001110 1
1$
#508
0$
#509
b11001111 1
1$
#510
0$
#511
b11010000 1
1$
#512
0$
#513
b11010001 1
1$
#514
0$
#515
b11010010 1
1$
#516
0$
#517
b11010011 1
1$
#518
0$
#519
b11010100 1
1$
#520
0$
#521
b11010101 1
1$
#522
0$
#523
b11010110 1
1$
#524
0$
#525
b11010111 1
1$
#526
0$
#527
b11011000 1
1$
#528
0$
#529
b11011001 1
1$
#530
0$
#531
b11011010 1
1$
#532
0$
#533
b11011011 1
1$
#534
0$
#535
b11011100 1
1$
#536
0$
#537
b11011101 1
1$
#538
0$
#539
b11011110 1
1$
#540
0$
#541
b11011111 1
1$
#542
0$
#543
b11100000 1
1$
#544
0$
#545
b11100001 1
1$
#546
0$
#547
b11100010 1
1$
#548
0$
#549
b11100011 1
1$
#550
0$
#551
b11100100 1
1$
#552
0$
#553
b11100101 1
1$
#554
0$
#555
b11100110 1
1$
#556
0$
#557
b11100111 1
1$
#558
0$
#559
b11101000 1
1$
#560
0$
#561
b11101001 1
1$
#562
0$
#563
b11101010 1
1$
#564
0$
#565
b11101011 1
1$
#566
0$
#567
b11101100 1
1$
#568
0$
#569
b11101101 1
1$
#570
0$
#571
b11101110 1
1$
#572
0$
#573
b11101111 1
1$
#574
0$
#575
b11110000 1
1$
#576
0$
#577
b11110001 1
1$
#578
0$
#579
b11110010 1
1$
#580
0$
#581
b11110011 1
1$
#582
0$
#583
b11110100 1
1$
#584
0$
#585
b11110101 1
1$
#586
0$
#587
b11110110 1
1$
#588
0$
#589
b11110111 1
1$
#590
0$
#591
b11111000 1
1$
#592
0$
#593
b11111001 1
1$
#594
0$
#595
b11111010 1
1$
#596
0$
#597
b11111011 1
1$
#598
0$
#599
b11111100 1
1$
#600
0$
#601
b11111101 1
1$
#602
0$
#603
b11111110 1
1$
#604
0$
#605
b11111111 1
1$
#606
0$
#607
b100000000 1
1$
#608
0$
#609
b100000001 1
1$
#610
0$
#611
b100000010 1
1$
#612
0$
#613
b100000011 1
1$
#614
0$
#615
b100000100 1
1$
#616
0$
#617
b100000101 1
1$
#618
0$
#619
b100000110 1
1$
#620
0$
#621
b100000111 1
1$
#622
0$
#623
b100001000 1
1$
#624
0$
#625
b100001001 1
1$
#626
0$
#627
b100001010 1
1$
#628
0$
#629
b100001011 1
1$
#630
0$
#631
b100001100 1
1$
#632
0$
#633
b100001101 1
1$
#634
0$
#635
b100001110 1
1$
#636
0$
#637
b100001111 1
1$
#638
0$
#639
b100010000 1
1$
#640
0$
#641
b100010001 1
1$
#642
0$
#643
b100010010 1
1$
#644
0$
#645
b100010011 1
1$
#646
0$
#647
b100010100 1
1$
#648
0$
#649
b100010101 1
1$
#650
0$
#651
b100010110 1
1$
#652
0$
#653
b100010111 1
1$
#654
0$
#655
b100011000 1
1$
#656
0$
#657
b100011001 1
1$
#658
0$
#659
b100011010 1
1$
#660
0$
#661
b100011011 1
1$
#662
0$
#663
b100011100 1
1$
#664
0$
#665
b100011101 1
1$
#666
0$
#667
b100011110 1
1$
#668
0$
#669
b100011111 1
1$
#670
0$
#671
b100100000 1
1$
#672
0$
#673
b100100001 1
1$
#674
0$
#675
b100100010 1
1$
#676
0$
#677
b100100011 1
1$
#678
0$
#679
b100100100 1
1$
#680
0$
#681
b100100101 1
1$
#682
0$
#683
b100100110 1
1$
#684
0$
#685
b100100111 1
1$
#686
0$
#687
b100101000 1
1$
#688
0$
#689
b100101001 1
1$
#690
0$
#691
b100101010 1
1$
#692
0$
#693
b100101011 1
1$
#694
0$
#695
b100101100 1
1$
#696
0$
#697
b100101101 1
1$
#698
0$
#699
b100101110 1
1$
#700
0$
#701
b100101111 1
1$
#702
0$
#703
b100110000 1
1$
#704
0$
#705
b100110001 1
1$
#706
0$
#707
b100110010 1
1$
#708
0$
#709
b100110011 1
1$
#710
0$
#711
b100110100 1
1$
#712
0$
#713
b100110101 1
1$
#714
0$
#715
b100110110 1
1$
#716
0$
#717
b100110111 1
1$
#718
0$
#719
b100111000 1
1$
#720
0$
#721
b100111001 1
1$
#722
0$
#723
b100111010 1
1$
#724
0$
#725
b100111011 1
1$
#726
0$
#727
b100111100 1
1$
#728
0$
#729
b100111101 1
1$
#730
0$
#731
b100111110 1
1$
#732
0$
#733
b100111111 1
1$
#734
0$
#735
b101000000 1
1$
#736
0$
#737
b101000001 1
1$
#738
0$
#739
b101000010 1
1$
#740
0$
#741
b101000011 1
1$
#742
0$
#743
b101000100 1
1$
#744
0$
#745
b101000101 1
1$
#746
0$
#747
b101000110 1
1$
#748
0$
#749
b101000111 1
1$
#750
0$
#751
b101001000 1
1$
#752
0$
#753
b101001001 1
1$
#754
0$
#755
b101001010 1
1$
#756
0$
#757
b101001011 1
1$
#758
0$
#759
b101001100 1
1$
#760
0$
#761
b101001101 1
1$
#762
0$
#763
b101001110 1
1$
#764
0$
#765
b101001111 1
1$
#766
0$
#767
b101010000 1
1$
#768
0$
#769
b101010001 1
1$
#770
0$
#771
b101010010 1
1$
#772
0$
#773
b101010011 1
1$
#774
0$
#775
b101010100 1
1$
#776
0$
#777
b101010101 1
1$
#778
0$
#779
b101010110 1
1$
#780
0$
#781
b101010111 1
1$
#782
0$
#783
b101011000 1
1$
#784
0$
#785
b101011001 1
1$
#786
0$
#787
b101011010 1
1$
#788
0$
#789
b101011011 1
1$
#790
0$
#791
b101011100 1
1$
#792
0$
#793
b101011101 1
1$
#794
0$
#795
b101011110 1
1$
#796
0$
#797
b101011111 1
1$
#798
0$
#799
b101100000 1
1$
#800
0$
#801
b101100001 1
1$
#802
0$
#803
b101100010 1
1$
#804
0$
#805
b101100011 1
1$
#806
0$
#807
b101100100 1
1$
#808
0$
#809
b101100101 1
1$
#810
0$
#811
b101100110 1
1$
#812
0$
#813
b101100111 1
1$
#814
0$
#815
b101101000 1
1$
#816
0$
#817
b101101001 1
1$
#818
0$
#819
b101101010 1
1$
#820
0$
#821
b101101011 1
1$
#822
0$
#823
b101101100 1
1$
#824
0$
#825
b101101101 1
1$
#826
0$
#827
b101101110 1
1$
#828
0$
#829
b101101111 1
1$
#830
0$
#831
b101110000 1
1$
#832
0$
#833
b101110001 1
1$
#834
0$
#835
b101110010 1
1$
#836
0$
#837
b101110011 1
1$
#838
0$
#839
b101110100 1
1$
#840
0$
#841
b101110101 1
1$
#842
0$
#843
b101110110 1
1$
#844
0$
#845
b101110111 1
1$
#846
0$
#847
b101111000 1
1$
#848
0$
#849
b101111001 1
1$
#850
0$
#851
b101111010 1
1$
#852
0$
#853
b101111011 1
1$
#854
0$
#855
b101111100 1
1$
#856
0$
#857
b101111101 1
1$
#858
0$
#859
b101111110 1
1$
#860
0$
#861
b101111111 1
1$
#862
0$
#863
b110000000 1
1$
#864
0$
#865
b110000001 1
1$
#866
0$
#867
b110000010 1
1$
#868
0$
#869
b110000011 1
1$
#870
0$
#871
b110000100 1
1$
#872
0$
#873
b110000101 1
1$
#874
0$
#875
b110000110 1
1$
#876
0$
#877
b110000111 1
1$
#878
0$
#879
b110001000 1
1$
#880
0$
#881
b110001001 1
1$
#882
0$
#883
b110001010 1
1$
#884
0$
#885
b110001011 1
1$
#886
0$
#887
b110001100 1
1$
#888
0$
#889
b110001101 1
1$
#890
0$
#891
b110001110 1
1$
#892
0$
#893
b110001111 1
1$
#894
0$
#895
b110010000 1
1$
#896
0$
#897
b110010001 1
1$
#898
0$
#899
b110010010 1
1$
#900
0$
#901
b110010011 1
1$
#902
0$
#903
b110010100 1
1$
#904
0$
#905
b110010101 1
1$
#906
0$
#907
b110010110 1
1$
#908
0$
#909
b110010111 1
1$
#910
0$
#911
b110011000 1
1$
#912
0$
#913
b110011001 1
1$
#914
0$
#915
b110011010 1
1$
#916
0$
#917
b110011011 1
1$
#918
0$
#919
b110011100 1
1$
#920
0$
#921
b110011101 1
1$
#922
0$
#923
b110011110 1
1$
#924
0$
#925
b110011111 1
1$
#926
0$
#927
b110100000 1
1$
#928
0$
#929
b110100001 1
1$
#930
0$
#931
b110100010 1
1$
#932
0$
#933
b110100011 1
1$
#934
0$
#935
b110100100 1
1$
#936
0$
#937
b110100101 1
1$
#938
0$
#939
b110100110 1
1$
#940
0$
#941
b110100111 1
1$
#942
0$
#943
b110101000 1
1$
#944
0$
#945
b110101001 1
1$
#946
0$
#947
b110101010 1
1$
#948
0$
#949
b110101011 1
1$
#950
0$
#951
b110101100 1
1$
#952
0$
#953
b110101101 1
1$
#954
0$
#955
b110101110 1
1$
#956
0$
#957
b110101111 1
1$
#958
0$
#959
b110110000 1
1$
#960
0$
#961
b110110001 1
1$
#962
0$
#963
b110110010 1
1$
#964
0$
#965
b110110011 1
1$
#966
0$
#967
b110110100 1
1$
#968
0$
#969
b110110101 1
1$
#970
0$
#971
b110110110 1
1$
#972
0$
#973
b110110111 1
1$
#974
0$
#975
b110111000 1
1$
#976
0$
#977
b110111001 1
1$
#978
0$
#979
b110111010 1
1$
#980
0$
#981
b110111011 1
1$
#982
0$
#983
b110111100 1
1$
#984
0$
#985
b110111101 1
1$
#986
0$
#987
b110111110 1
1$
#988
0$
#989
b110111111 1
1$
#990
0$
#991
b111000000 1
1$
#992
0$
#993
b111000001 1
1$
#994
0$
#995
b111000010 1
1$
#996
0$
#997
b111000011 1
1$
#998
0$
#999
b111000100 1
1$
#1000
0$
#1001
b111000101 1
1$
#1002
0$
#1003
b111000110 1
1$
#1004
0$
#1005
b111000111 1
1$
#1006
0$
#1007
b111001000 1
1$
#1008
0$
#1009
b111001001 1
1$
#1010
0$
#1011
b111001010 1
1$
#1012
0$
#1013
b111001011 1
1$
#1014
0$
#1015
b111001100 1
1$
#1016
0$
#1017
b111001101 1
1$
#1018
0$
#1019
b111001110 1
1$
#1020
0$
#1021
b111001111 1
1$
#1022
0$
#1023
b111010000 1
1$
#1024
0$
#1025
b111010001 1
1$
#1026
0$
#1027
b111010010 1
1$
#1028
0$
#1029
b111010011 1
1$
#1030
0$
#1031
b111010100 1
1$
#1032
0$
#1033
b111010101 1
1$
#1034
0$
#1035
b111010110 1
1$
#1036
0$
#1037
b111010111 1
1$
#1038
0$
#1039
b111011000 1
1$
#1040
0$
#1041
b111011001 1
1$
#1042
0$
#1043
b111011010 1
1$
#1044
0$
#1045
b111011011 1
1$
#1046
0$
#1047
b111011100 1
1$
#1048
0$
#1049
b111011101 1
1$
#1050
0$
#1051
b111011110 1
1$
#1052
0$
#1053
b111011111 1
1$
#1054
0$
#1055
b111100000 1
1$
#1056
0$
#1057
b111100001 1
1$
#1058
0$
#1059
b111100010 1
1$
#1060
0$
#1061
b111100011 1
1$
#1062
0$
#1063
b111100100 1
1$
#1064
0$
#1065
b111100101 1
1$
#1066
0$
#1067
b111100110 1
1$
#1068
0$
#1069
b111100111 1
1$
#1070
0$
#1071
b111101000 1
1$
#1072
0$
#1073
b111101001 1
1$
#1074
0$
#1075
b111101010 1
1$
#1076
0$
#1077
b111101011 1
1$
#1078
0$
#1079
b111101100 1
1$
#1080
0$
#1081
b111101101 1
1$
#1082
0$
#1083
b111101110 1
1$
#1084
0$
#1085
b111101111 1
1$
#1086
0$
#1087
b111110000 1
1$
#1088
0$
#1089
b111110001 1
1$
#1090
0$
#1091
b111110010 1
1$
#1092
0$
#1093
b111110011 1
1$
#1094
0$
#1095
b111110100 1
1$
#1096
0$
#1097
b111110101 1
1$
#1098
0$
#1099
b111110110 1
1$
#1100
0$
#1101
b111110111 1
1$
#1102
0$
#1103
b111111000 1
1$
#1104
0$
#1105
b111111001 1
1$
#1106
0$
#1107
b111111010 1
1$
#1108
0$
#1109
b111111011 1
1$
#1110
0$
#1111
b111111100 1
1$
#1112
0$
#1113
b111111101 1
1$
#1114
0$
#1115
b111111110 1
1$
#1116
0$
#1117
b111111111 1
1$
#1118
0$
#1119
b1000000000 1
1$
#1120
0$
#1121
b1000000001 1
1$
#1122
0$
#1123
b1000000010 1
1$
#1124
0$
#1125
b1000000011 1
1$
#1126
0$
#1127
b1000000100 1
1$
#1128
0$
#1129
b1000000101 1
1$
#1130
0$
#1131
b1000000110 1
1$
#1132
0$
#1133
b1000000111 1
1$
#1134
0$
#1135
b1000001000 1
1$
#1136
0$
#1137
b1000001001 1
1$
#1138
0$
#1139
b1000001010 1
1$
#1140
0$
#1141
b1000001011 1
1$
#1142
0$
#1143
b1000001100 1
1$
#1144
0$
#1145
b1000001101 1
1$
#1146
0$
#1147
b1000001110 1
1$
#1148
0$
#1149
b1000001111 1
1$
#1150
0$
#1151
b1000010000 1
1$
#1152
0$
#1153
b1000010001 1
1$
#1154
0$
#1155
b1000010010 1
1$
#1156
0$
#1157
b1000010011 1
1$
#1158
0$
#1159
b1000010100 1
1$
#1160
0$
#1161
b1000010101 1
1$
#1162
0$
#1163
b1000010110 1
1$
#1164
0$
#1165
b1000010111 1
1$
#1166
0$
#1167
b1000011000 1
1$
#1168
0$
#1169
b1000011001 1
1$
#1170
0$
#1171
b1000011010 1
1$
#1172
0$
#1173
b1000011011 1
1$
#1174
0$
#1175
b1000011100 1
1$
#1176
0$
#1177
b1000011101 1
1$
#1178
0$
#1179
b1000011110 1
1$
#1180
0$
#1181
b1000011111 1
1$
#1182
0$
#1183
b1000100000 1
1$
#1184
0$
#1185
b1000100001 1
1$
#1186
0$
#1187
b1000100010 1
1$
#1188
0$
#1189
b1000100011 1
1$
#1190
0$
#1191
b1000100100 1
1$
#1192
0$
#1193
b1000100101 1
1$
#1194
0$
#1195
b1000100110 1
1$
#1196
0$
#1197
b1000100111 1
1$
#1198
0$
#1199
b1000101000 1
1$
#1200
0$
#1201
b1000101001 1
1$
#1202
0$
#1203
b1000101010 1
1$
#1204
0$
#1205
b1000101011 1
1$
#1206
0$
#1207
b1000101100 1
1$
#1208
0$
#1209
b1000101101 1
1$
#1210
0$
#1211
b1000101110 1
1$
#1212
0$
#1213
b1000101111 1
1$
#1214
0$
#1215
b1000110000 1
1$
#1216
0$
#1217
b1000110001 1
1$
#1218
0$
#1219
b1000110010 1
1$
#1220
0$
#1221
b1000110011 1
1$
